<?xml version="1.0" encoding="UTF-8"?>
<objects serializationModel="Studio.02.02.00">
	<object class="AudioFile" id="{811b6645-3509-44d0-ab16-5a9e9067239e}">
		<property name="assetPath">
			<value>26284_brake-5.ogg</value>
		</property>
		<property name="frequencyInKHz">
			<value>22.0499992</value>
		</property>
		<property name="channelCount">
			<value>1</value>
		</property>
		<property name="length">
			<value>1.2194557823129251</value>
		</property>
		<relationship name="masterAssetFolder">
			<destination>{871428f9-d9c6-42cb-9921-f61991f13b4f}</destination>
		</relationship>
	</object>
</objects>
