<?xml version="1.0" encoding="UTF-8"?>
<objects serializationModel="Studio.02.02.00">
	<object class="AudioFile" id="{f34413ca-e552-42c3-af99-509c8550864b}">
		<property name="assetPath">
			<value>6dg_silnik_start.ogg</value>
		</property>
		<property name="isStreaming">
			<value>true</value>
		</property>
		<property name="frequencyInKHz">
			<value>22.0499992</value>
		</property>
		<property name="channelCount">
			<value>1</value>
		</property>
		<property name="length">
			<value>20.248027210884352</value>
		</property>
		<relationship name="masterAssetFolder">
			<destination>{871428f9-d9c6-42cb-9921-f61991f13b4f}</destination>
		</relationship>
	</object>
</objects>
